pytorch_fcd/__init__.py
pytorch_fcd/__main__.py
pytorch_fcd/fcd_score.py
pytorch_fcd-1.0.1.dev1.dist-info/LICENSE
pytorch_fcd-1.0.1.dev1.dist-info/METADATA
pytorch_fcd-1.0.1.dev1.dist-info/WHEEL
pytorch_fcd-1.0.1.dev1.dist-info/entry_points.txt
pytorch_fcd-1.0.1.dev1.dist-info/top_level.txt
pytorch_fcd-1.0.1.dev1.dist-info/RECORD
