Metadata-Version: 2.1
Name: pytorch-fcd
Version: 1.0.1.dev1
Summary: Package for calculating Frechet CLIP Distance (FCD) using PyTorch
Home-page: https://github.com/syang-lab/FCD_Score
Author: Shan Yang
Classifier: Development Status :: 3 - Alpha
Classifier: Programming Language :: Python :: 3
Classifier: License :: OSI Approved :: Apache Software License
Requires-Python: >=3.5
License-File: LICENSE
Requires-Dist: ftfy
Requires-Dist: regex
Requires-Dist: numpy
Requires-Dist: pillow
Requires-Dist: scipy
Requires-Dist: torch >=1.7.1
Requires-Dist: torchvision >=0.8.2
Requires-Dist: clip
